trade_models/__init__.py
trade_models/strategy_models.py
user_models/__init__.py
user_models/exchange_models.py
buzz_models-1.0.0.dist-info/METADATA
buzz_models-1.0.0.dist-info/WHEEL
buzz_models-1.0.0.dist-info/top_level.txt
buzz_models-1.0.0.dist-info/RECORD
