Metadata-Version: 2.1
Name: buzz-models
Version: 1.0.0
Summary: buzz的数据库模型
Home-page: https://github.com/yourusername/shared_models
Author: mails
Author-email: s644100298@gmail.com
Requires-Dist: sqlmodel (>=0.0.6)
Requires-Dist: sqlalchemy[asyncio] (>=1.4)
